print_err/__init__.py
print_err/__main__.py
print_err/print_err.py
print_err/version.py
tests/test_print_err.py
print_err-0.0.1.dist-info/LICENSE
print_err-0.0.1.dist-info/METADATA
print_err-0.0.1.dist-info/WHEEL
print_err-0.0.1.dist-info/entry_points.txt
print_err-0.0.1.dist-info/top_level.txt
print_err-0.0.1.dist-info/RECORD
