Metadata-Version: 2.1
Name: print-err
Version: 0.0.1
Summary: Print to standard error optionally exiting with a code
Home-page: https://github.com/joaompinto/print_err
Author: João Pinto
Author-email: lamego.pinto@gmail.com
License: MIT
Platform: UNKNOWN
